zih_ldap/__init__.py
zih_ldap/conftest.py
zih_ldap/connection.py
zih_ldap/models.py
zih_ldap/py.typed
zih_ldap/pydantic_validators.py
zih_ldap/test_models.py
zih_ldap-0.2.4.dist-info/LICENSE
zih_ldap-0.2.4.dist-info/METADATA
zih_ldap-0.2.4.dist-info/WHEEL
zih_ldap-0.2.4.dist-info/RECORD
