Metadata-Version: 2.3
Name: zih-ldap
Version: 0.2.4
Summary: Wrapper integrating LDAP and Pydantic for TU Dresden
License: MIT
Author: Ansgar Burchardt
Author-email: ansgar.burchardt@tu-dresden.de
Requires-Python: >=3.11
Classifier: Programming Language :: Python :: 3
Classifier: Operating System :: OS Independent
Requires-Dist: ldap3 (>=2.9.1,<3.0.0)
Requires-Dist: pydantic (>=2.11.5,<3.0.0)
Project-URL: Repository, https://gitlab.hrz.tu-chemnitz.de/zih/sde/zih-ldap
